[
  {
    "inputs": [
      {
        "internalType": "address",
        "name": "_owner",
        "type": "address"
      }
    ],
    "stateMutability": "nonpayable",
    "type": "constructor"
  },
  {
    "inputs": [
      {
        "internalType": "address",
        "name": "",
        "type": "address"
      }
    ],
    "name": "accountToTokenKey",
    "outputs": [
      {
        "internalType": "bytes32",
        "name": "originAddress",
        "type": "bytes32"
      },
      {
        "internalType": "uint256",
        "name": "collectibleId",
        "type": "uint256"
      },
      {
        "internalType": "enum TokenDefs.TokenType",
        "name": "tokenType",
        "type": "uint8"
      },
      {
        "internalType": "enum TokenDefs.BlockchainType",
        "name": "blockchainType",
        "type": "uint8"
      },
      {
        "internalType": "uint32",
        "name": "endpointId",
        "type": "uint32"
      }
    ],
    "stateMutability": "view",
    "type": "function"
  },
  {
    "inputs": [
      {
        "internalType": "bytes32",
        "name": "templateId",
        "type": "bytes32"
      }
    ],
    "name": "adapterTemplates",
    "outputs": [
      {
        "internalType": "address",
        "name": "implementationAddress",
        "type": "address"
      },
      {
        "internalType": "enum FactoryLogic.AdapterType",
        "name": "adapterType",
        "type": "uint8"
      }
    ],
    "stateMutability": "view",
    "type": "function"
  },
  {
    "inputs": [
      {
        "internalType": "address",
        "name": "user",
        "type": "address"
      },
      {
        "internalType": "address",
        "name": "builder",
        "type": "address"
      }
    ],
    "name": "approvals",
    "outputs": [
      {
        "internalType": "uint256",
        "name": "packedApprovals",
        "type": "uint256"
      }
    ],
    "stateMutability": "view",
    "type": "function"
  },
  {
    "inputs": [
      {
        "internalType": "address",
        "name": "builder",
        "type": "address"
      },
      {
        "components": [
          {
            "internalType": "uint8",
            "name": "activity",
            "type": "uint8"
          },
          {
            "internalType": "uint16",
            "name": "maxFeeBps",
            "type": "uint16"
          }
        ],
        "internalType": "struct FeesConfigV2.ApprovalEntry[]",
        "name": "entries",
        "type": "tuple[]"
      }
    ],
    "name": "approveBuilderFees",
    "outputs": [],
    "stateMutability": "nonpayable",
    "type": "function"
  },
  {
    "inputs": [
      {
        "internalType": "string",
        "name": "name",
        "type": "string"
      },
      {
        "internalType": "string",
        "name": "uri",
        "type": "string"
      },
      {
        "internalType": "bool",
        "name": "inviteOnly",
        "type": "bool"
      },
      {
        "internalType": "address",
        "name": "receiver",
        "type": "address"
      }
    ],
    "name": "createHub",
    "outputs": [
      {
        "components": [
          {
            "internalType": "bytes32",
            "name": "originAddress",
            "type": "bytes32"
          },
          {
            "internalType": "uint256",
            "name": "collectibleId",
            "type": "uint256"
          },
          {
            "internalType": "enum TokenDefs.TokenType",
            "name": "tokenType",
            "type": "uint8"
          },
          {
            "internalType": "enum TokenDefs.BlockchainType",
            "name": "blockchainType",
            "type": "uint8"
          },
          {
            "internalType": "uint32",
            "name": "endpointId",
            "type": "uint32"
          }
        ],
        "internalType": "struct TokenKey",
        "name": "key",
        "type": "tuple"
      },
      {
        "internalType": "address",
        "name": "account",
        "type": "address"
      }
    ],
    "stateMutability": "nonpayable",
    "type": "function"
  },
  {
    "inputs": [
      {
        "components": [
          {
            "internalType": "bytes32",
            "name": "templateId",
            "type": "bytes32"
          },
          {
            "internalType": "bytes32",
            "name": "saltEvm",
            "type": "bytes32"
          },
          {
            "internalType": "bytes32",
            "name": "saltSolana",
            "type": "bytes32"
          },
          {
            "internalType": "string",
            "name": "name",
            "type": "string"
          },
          {
            "internalType": "string",
            "name": "symbol",
            "type": "string"
          },
          {
            "internalType": "string",
            "name": "tokenUri",
            "type": "string"
          },
          {
            "internalType": "bool",
            "name": "isTransferable",
            "type": "bool"
          },
          {
            "internalType": "bool",
            "name": "createTBA",
            "type": "bool"
          }
        ],
        "internalType": "struct FactoryLogic.TokenParams",
        "name": "tokenParams",
        "type": "tuple"
      },
      {
        "components": [
          {
            "internalType": "bool",
            "name": "isTradeable",
            "type": "bool"
          },
          {
            "internalType": "uint256",
            "name": "amountIn",
            "type": "uint256"
          },
          {
            "internalType": "uint256",
            "name": "maxAmountIn",
            "type": "uint256"
          },
          {
            "internalType": "uint256",
            "name": "tokensOut",
            "type": "uint256"
          },
          {
            "components": [
              {
                "internalType": "bool",
                "name": "phase1RoleRequired",
                "type": "bool"
              },
              {
                "internalType": "bool",
                "name": "phase2RoleRequired",
                "type": "bool"
              },
              {
                "internalType": "bool",
                "name": "phase3RoleRequired",
                "type": "bool"
              },
              {
                "internalType": "bool",
                "name": "phase1ParentRoleRequired",
                "type": "bool"
              },
              {
                "internalType": "bool",
                "name": "phase2ParentRoleRequired",
                "type": "bool"
              },
              {
                "internalType": "bool",
                "name": "phase3ParentRoleRequired",
                "type": "bool"
              },
              {
                "internalType": "uint40",
                "name": "phase1TokenLimitPerUser",
                "type": "uint40"
              },
              {
                "internalType": "uint40",
                "name": "phase2TokenLimitPerUser",
                "type": "uint40"
              },
              {
                "internalType": "uint40",
                "name": "phase3TokenLimitPerUser",
                "type": "uint40"
              },
              {
                "internalType": "uint32",
                "name": "startBlock",
                "type": "uint32"
              }
            ],
            "internalType": "struct FactoryLogic.SaleParams",
            "name": "saleParams",
            "type": "tuple"
          },
          {
            "internalType": "uint256",
            "name": "poolType",
            "type": "uint256"
          },
          {
            "internalType": "uint32[]",
            "name": "migrationEndpoints",
            "type": "uint32[]"
          }
        ],
        "internalType": "struct FactoryLogic.TradingParams",
        "name": "tradingParams",
        "type": "tuple"
      },
      {
        "internalType": "address",
        "name": "receiver",
        "type": "address"
      }
    ],
    "name": "createToken",
    "outputs": [
      {
        "components": [
          {
            "internalType": "bytes32",
            "name": "originAddress",
            "type": "bytes32"
          },
          {
            "internalType": "uint256",
            "name": "collectibleId",
            "type": "uint256"
          },
          {
            "internalType": "enum TokenDefs.TokenType",
            "name": "tokenType",
            "type": "uint8"
          },
          {
            "internalType": "enum TokenDefs.BlockchainType",
            "name": "blockchainType",
            "type": "uint8"
          },
          {
            "internalType": "uint32",
            "name": "endpointId",
            "type": "uint32"
          }
        ],
        "internalType": "struct TokenKey",
        "name": "key",
        "type": "tuple"
      },
      {
        "components": [
          {
            "internalType": "bytes32",
            "name": "originAddress",
            "type": "bytes32"
          },
          {
            "internalType": "uint256",
            "name": "collectibleId",
            "type": "uint256"
          },
          {
            "internalType": "enum TokenDefs.TokenType",
            "name": "tokenType",
            "type": "uint8"
          },
          {
            "internalType": "enum TokenDefs.BlockchainType",
            "name": "blockchainType",
            "type": "uint8"
          },
          {
            "internalType": "uint32",
            "name": "endpointId",
            "type": "uint32"
          }
        ],
        "internalType": "struct TokenKey",
        "name": "titleKey",
        "type": "tuple"
      },
      {
        "internalType": "address",
        "name": "account",
        "type": "address"
      }
    ],
    "stateMutability": "nonpayable",
    "type": "function"
  },
  {
    "inputs": [
      {
        "components": [
          {
            "internalType": "bytes32",
            "name": "templateId",
            "type": "bytes32"
          },
          {
            "internalType": "bytes32",
            "name": "saltEvm",
            "type": "bytes32"
          },
          {
            "internalType": "bytes32",
            "name": "saltSolana",
            "type": "bytes32"
          },
          {
            "internalType": "string",
            "name": "name",
            "type": "string"
          },
          {
            "internalType": "string",
            "name": "symbol",
            "type": "string"
          },
          {
            "internalType": "string",
            "name": "tokenUri",
            "type": "string"
          },
          {
            "internalType": "bool",
            "name": "isTransferable",
            "type": "bool"
          },
          {
            "internalType": "bool",
            "name": "createTBA",
            "type": "bool"
          }
        ],
        "internalType": "struct FactoryLogic.TokenParams",
        "name": "tokenParams",
        "type": "tuple"
      },
      {
        "internalType": "bytes32",
        "name": "adapterTemplateId",
        "type": "bytes32"
      },
      {
        "internalType": "address",
        "name": "externalTokenAddress",
        "type": "address"
      }
    ],
    "name": "createTokenExternal",
    "outputs": [
      {
        "components": [
          {
            "internalType": "bytes32",
            "name": "originAddress",
            "type": "bytes32"
          },
          {
            "internalType": "uint256",
            "name": "collectibleId",
            "type": "uint256"
          },
          {
            "internalType": "enum TokenDefs.TokenType",
            "name": "tokenType",
            "type": "uint8"
          },
          {
            "internalType": "enum TokenDefs.BlockchainType",
            "name": "blockchainType",
            "type": "uint8"
          },
          {
            "internalType": "uint32",
            "name": "endpointId",
            "type": "uint32"
          }
        ],
        "internalType": "struct TokenKey",
        "name": "key",
        "type": "tuple"
      },
      {
        "internalType": "address",
        "name": "adapter",
        "type": "address"
      }
    ],
    "stateMutability": "nonpayable",
    "type": "function"
  },
  {
    "inputs": [
      {
        "internalType": "address",
        "name": "referee",
        "type": "address"
      }
    ],
    "name": "deactivateReferralDiscount",
    "outputs": [],
    "stateMutability": "nonpayable",
    "type": "function"
  },
  {
    "inputs": [
      {
        "internalType": "address",
        "name": "referee",
        "type": "address"
      }
    ],
    "name": "deactivateReferralReward",
    "outputs": [],
    "stateMutability": "nonpayable",
    "type": "function"
  },
  {
    "inputs": [],
    "name": "defaultRoleId",
    "outputs": [
      {
        "internalType": "uint256",
        "name": "",
        "type": "uint256"
      }
    ],
    "stateMutability": "view",
    "type": "function"
  },
  {
    "inputs": [
      {
        "internalType": "bytes32",
        "name": "name",
        "type": "bytes32"
      },
      {
        "internalType": "bytes32",
        "name": "salt",
        "type": "bytes32"
      },
      {
        "internalType": "bytes",
        "name": "creationCode",
        "type": "bytes"
      },
      {
        "internalType": "bytes",
        "name": "constructorArgs",
        "type": "bytes"
      },
      {
        "internalType": "uint256",
        "name": "value",
        "type": "uint256"
      }
    ],
    "name": "deployContract",
    "outputs": [
      {
        "internalType": "address",
        "name": "deployed",
        "type": "address"
      }
    ],
    "stateMutability": "nonpayable",
    "type": "function"
  },
  {
    "inputs": [],
    "name": "endpoint",
    "outputs": [
      {
        "internalType": "contract ILayerZeroEndpointV2",
        "name": "",
        "type": "address"
      }
    ],
    "stateMutability": "view",
    "type": "function"
  },
  {
    "inputs": [
      {
        "internalType": "TokenId",
        "name": "id",
        "type": "bytes32"
      }
    ],
    "name": "evmAddress",
    "outputs": [
      {
        "internalType": "address",
        "name": "evmAddress",
        "type": "address"
      }
    ],
    "stateMutability": "view",
    "type": "function"
  },
  {
    "inputs": [
      {
        "internalType": "TokenId",
        "name": "id",
        "type": "bytes32"
      }
    ],
    "name": "evmSalt",
    "outputs": [
      {
        "internalType": "bytes32",
        "name": "evmSalt",
        "type": "bytes32"
      }
    ],
    "stateMutability": "view",
    "type": "function"
  },
  {
    "inputs": [
      {
        "internalType": "address",
        "name": "account",
        "type": "address"
      }
    ],
    "name": "getAccountToken",
    "outputs": [
      {
        "components": [
          {
            "internalType": "bytes32",
            "name": "originAddress",
            "type": "bytes32"
          },
          {
            "internalType": "uint256",
            "name": "collectibleId",
            "type": "uint256"
          },
          {
            "internalType": "enum TokenDefs.TokenType",
            "name": "tokenType",
            "type": "uint8"
          },
          {
            "internalType": "enum TokenDefs.BlockchainType",
            "name": "blockchainType",
            "type": "uint8"
          },
          {
            "internalType": "uint32",
            "name": "endpointId",
            "type": "uint32"
          }
        ],
        "internalType": "struct TokenKey",
        "name": "key",
        "type": "tuple"
      }
    ],
    "stateMutability": "view",
    "type": "function"
  },
  {
    "inputs": [
      {
        "internalType": "address",
        "name": "user",
        "type": "address"
      },
      {
        "internalType": "address",
        "name": "builder",
        "type": "address"
      },
      {
        "internalType": "uint8",
        "name": "activity",
        "type": "uint8"
      }
    ],
    "name": "getApprovedFee",
    "outputs": [
      {
        "internalType": "uint16",
        "name": "maxFeeBps",
        "type": "uint16"
      }
    ],
    "stateMutability": "view",
    "type": "function"
  },
  {
    "inputs": [
      {
        "internalType": "bytes32",
        "name": "identifier",
        "type": "bytes32"
      }
    ],
    "name": "getContract",
    "outputs": [
      {
        "internalType": "address",
        "name": "contractAddress",
        "type": "address"
      }
    ],
    "stateMutability": "view",
    "type": "function"
  },
  {
    "inputs": [
      {
        "internalType": "address",
        "name": "contractAddress",
        "type": "address"
      }
    ],
    "name": "getContractName",
    "outputs": [
      {
        "internalType": "bytes32",
        "name": "name",
        "type": "bytes32"
      }
    ],
    "stateMutability": "view",
    "type": "function"
  },
  {
    "inputs": [
      {
        "internalType": "address",
        "name": "referee",
        "type": "address"
      }
    ],
    "name": "getReferralStatus",
    "outputs": [
      {
        "components": [
          {
            "internalType": "address",
            "name": "referrer",
            "type": "address"
          },
          {
            "internalType": "bool",
            "name": "rewardActive",
            "type": "bool"
          },
          {
            "internalType": "bool",
            "name": "discountActive",
            "type": "bool"
          }
        ],
        "internalType": "struct ReferralsConfig.ReferralStatus",
        "name": "status",
        "type": "tuple"
      }
    ],
    "stateMutability": "view",
    "type": "function"
  },
  {
    "inputs": [
      {
        "internalType": "address",
        "name": "referee",
        "type": "address"
      }
    ],
    "name": "getReferrer",
    "outputs": [
      {
        "internalType": "address",
        "name": "referrer",
        "type": "address"
      }
    ],
    "stateMutability": "view",
    "type": "function"
  },
  {
    "inputs": [
      {
        "components": [
          {
            "internalType": "bytes32",
            "name": "originAddress",
            "type": "bytes32"
          },
          {
            "internalType": "uint256",
            "name": "collectibleId",
            "type": "uint256"
          },
          {
            "internalType": "enum TokenDefs.TokenType",
            "name": "tokenType",
            "type": "uint8"
          },
          {
            "internalType": "enum TokenDefs.BlockchainType",
            "name": "blockchainType",
            "type": "uint8"
          },
          {
            "internalType": "uint32",
            "name": "endpointId",
            "type": "uint32"
          }
        ],
        "internalType": "struct TokenKey",
        "name": "key",
        "type": "tuple"
      }
    ],
    "name": "getSalt",
    "outputs": [
      {
        "internalType": "bytes32",
        "name": "_evmSalt",
        "type": "bytes32"
      },
      {
        "internalType": "bytes32",
        "name": "_solanaSalt",
        "type": "bytes32"
      }
    ],
    "stateMutability": "view",
    "type": "function"
  },
  {
    "inputs": [
      {
        "components": [
          {
            "internalType": "bytes32",
            "name": "originAddress",
            "type": "bytes32"
          },
          {
            "internalType": "uint256",
            "name": "collectibleId",
            "type": "uint256"
          },
          {
            "internalType": "enum TokenDefs.TokenType",
            "name": "tokenType",
            "type": "uint8"
          },
          {
            "internalType": "enum TokenDefs.BlockchainType",
            "name": "blockchainType",
            "type": "uint8"
          },
          {
            "internalType": "uint32",
            "name": "endpointId",
            "type": "uint32"
          }
        ],
        "internalType": "struct TokenKey",
        "name": "key",
        "type": "tuple"
      }
    ],
    "name": "getTokenAccount",
    "outputs": [
      {
        "internalType": "address",
        "name": "account",
        "type": "address"
      }
    ],
    "stateMutability": "view",
    "type": "function"
  },
  {
    "inputs": [
      {
        "internalType": "address",
        "name": "tokenAddress",
        "type": "address"
      },
      {
        "internalType": "uint256",
        "name": "collectibleId",
        "type": "uint256"
      }
    ],
    "name": "getTokenId",
    "outputs": [
      {
        "internalType": "TokenId",
        "name": "tokenId",
        "type": "bytes32"
      }
    ],
    "stateMutability": "view",
    "type": "function"
  },
  {
    "inputs": [
      {
        "internalType": "TokenId",
        "name": "tokenId",
        "type": "bytes32"
      }
    ],
    "name": "getTokenKey",
    "outputs": [
      {
        "components": [
          {
            "internalType": "bytes32",
            "name": "originAddress",
            "type": "bytes32"
          },
          {
            "internalType": "uint256",
            "name": "collectibleId",
            "type": "uint256"
          },
          {
            "internalType": "enum TokenDefs.TokenType",
            "name": "tokenType",
            "type": "uint8"
          },
          {
            "internalType": "enum TokenDefs.BlockchainType",
            "name": "blockchainType",
            "type": "uint8"
          },
          {
            "internalType": "uint32",
            "name": "endpointId",
            "type": "uint32"
          }
        ],
        "internalType": "struct TokenKey",
        "name": "key",
        "type": "tuple"
      }
    ],
    "stateMutability": "view",
    "type": "function"
  },
  {
    "inputs": [
      {
        "internalType": "address",
        "name": "_owner",
        "type": "address"
      },
      {
        "internalType": "address",
        "name": "forwarder",
        "type": "address"
      },
      {
        "internalType": "address",
        "name": "_paymentToken",
        "type": "address"
      },
      {
        "internalType": "address",
        "name": "_protocolFeeTo",
        "type": "address"
      },
      {
        "internalType": "address",
        "name": "_endpoint",
        "type": "address"
      },
      {
        "internalType": "address",
        "name": "_swapRouter",
        "type": "address"
      }
    ],
    "name": "initialize",
    "outputs": [],
    "stateMutability": "nonpayable",
    "type": "function"
  },
  {
    "inputs": [
      {
        "internalType": "address",
        "name": "user",
        "type": "address"
      },
      {
        "internalType": "address",
        "name": "builder",
        "type": "address"
      },
      {
        "internalType": "uint8",
        "name": "activity",
        "type": "uint8"
      },
      {
        "internalType": "uint64",
        "name": "feeBps",
        "type": "uint64"
      }
    ],
    "name": "isBuilderFeeApproved",
    "outputs": [
      {
        "internalType": "bool",
        "name": "approved",
        "type": "bool"
      }
    ],
    "stateMutability": "view",
    "type": "function"
  },
  {
    "inputs": [
      {
        "internalType": "address",
        "name": "deployedContract",
        "type": "address"
      }
    ],
    "name": "isContractRegistered",
    "outputs": [
      {
        "internalType": "bool",
        "name": "",
        "type": "bool"
      }
    ],
    "stateMutability": "view",
    "type": "function"
  },
  {
    "inputs": [
      {
        "internalType": "address",
        "name": "",
        "type": "address"
      }
    ],
    "name": "isManager",
    "outputs": [
      {
        "internalType": "bool",
        "name": "",
        "type": "bool"
      }
    ],
    "stateMutability": "view",
    "type": "function"
  },
  {
    "inputs": [
      {
        "internalType": "TokenId",
        "name": "id",
        "type": "bytes32"
      }
    ],
    "name": "isRegistered",
    "outputs": [
      {
        "internalType": "bool",
        "name": "",
        "type": "bool"
      }
    ],
    "stateMutability": "view",
    "type": "function"
  },
  {
    "inputs": [
      {
        "internalType": "address",
        "name": "forwarder",
        "type": "address"
      }
    ],
    "name": "isTrustedForwarder",
    "outputs": [
      {
        "internalType": "bool",
        "name": "",
        "type": "bool"
      }
    ],
    "stateMutability": "view",
    "type": "function"
  },
  {
    "inputs": [],
    "name": "lastTokenId",
    "outputs": [
      {
        "internalType": "uint256",
        "name": "",
        "type": "uint256"
      }
    ],
    "stateMutability": "view",
    "type": "function"
  },
  {
    "inputs": [],
    "name": "name",
    "outputs": [
      {
        "internalType": "string",
        "name": "",
        "type": "string"
      }
    ],
    "stateMutability": "view",
    "type": "function"
  },
  {
    "inputs": [
      {
        "internalType": "bytes32",
        "name": "identifier",
        "type": "bytes32"
      },
      {
        "internalType": "address",
        "name": "newAddress",
        "type": "address"
      }
    ],
    "name": "overwriteContractAddress",
    "outputs": [],
    "stateMutability": "nonpayable",
    "type": "function"
  },
  {
    "inputs": [],
    "name": "owner",
    "outputs": [
      {
        "internalType": "address",
        "name": "",
        "type": "address"
      }
    ],
    "stateMutability": "view",
    "type": "function"
  },
  {
    "inputs": [
      {
        "components": [
          {
            "internalType": "bytes32",
            "name": "originAddress",
            "type": "bytes32"
          },
          {
            "internalType": "uint256",
            "name": "collectibleId",
            "type": "uint256"
          },
          {
            "internalType": "enum TokenDefs.TokenType",
            "name": "tokenType",
            "type": "uint8"
          },
          {
            "internalType": "enum TokenDefs.BlockchainType",
            "name": "blockchainType",
            "type": "uint8"
          },
          {
            "internalType": "uint32",
            "name": "endpointId",
            "type": "uint32"
          }
        ],
        "internalType": "struct TokenKey",
        "name": "key",
        "type": "tuple"
      }
    ],
    "name": "ownerOf",
    "outputs": [
      {
        "internalType": "address",
        "name": "owner",
        "type": "address"
      }
    ],
    "stateMutability": "nonpayable",
    "type": "function"
  },
  {
    "inputs": [],
    "name": "paymentToken",
    "outputs": [
      {
        "internalType": "address",
        "name": "",
        "type": "address"
      }
    ],
    "stateMutability": "view",
    "type": "function"
  },
  {
    "inputs": [],
    "name": "protocolBonusDurationBlocks",
    "outputs": [
      {
        "internalType": "uint16",
        "name": "",
        "type": "uint16"
      }
    ],
    "stateMutability": "view",
    "type": "function"
  },
  {
    "inputs": [],
    "name": "protocolBonusStartPercentageBps",
    "outputs": [
      {
        "internalType": "uint16",
        "name": "",
        "type": "uint16"
      }
    ],
    "stateMutability": "view",
    "type": "function"
  },
  {
    "inputs": [],
    "name": "protocolFeeTo",
    "outputs": [
      {
        "internalType": "address",
        "name": "",
        "type": "address"
      }
    ],
    "stateMutability": "view",
    "type": "function"
  },
  {
    "inputs": [
      {
        "internalType": "uint8",
        "name": "activity",
        "type": "uint8"
      }
    ],
    "name": "protocolFees",
    "outputs": [
      {
        "internalType": "uint16",
        "name": "protocolFeeBps",
        "type": "uint16"
      }
    ],
    "stateMutability": "view",
    "type": "function"
  },
  {
    "inputs": [
      {
        "internalType": "uint8",
        "name": "activity",
        "type": "uint8"
      }
    ],
    "name": "protocolLimits",
    "outputs": [
      {
        "internalType": "uint16",
        "name": "maxFeeBps",
        "type": "uint16"
      }
    ],
    "stateMutability": "view",
    "type": "function"
  },
  {
    "inputs": [],
    "name": "referralsController",
    "outputs": [
      {
        "internalType": "address",
        "name": "",
        "type": "address"
      }
    ],
    "stateMutability": "view",
    "type": "function"
  },
  {
    "inputs": [
      {
        "internalType": "bytes32",
        "name": "saltEvm",
        "type": "bytes32"
      },
      {
        "internalType": "bytes32",
        "name": "saltSolana",
        "type": "bytes32"
      },
      {
        "internalType": "bytes32",
        "name": "templateId",
        "type": "bytes32"
      },
      {
        "components": [
          {
            "internalType": "bytes32",
            "name": "originAddress",
            "type": "bytes32"
          },
          {
            "internalType": "uint256",
            "name": "collectibleId",
            "type": "uint256"
          },
          {
            "internalType": "enum TokenDefs.TokenType",
            "name": "tokenType",
            "type": "uint8"
          },
          {
            "internalType": "enum TokenDefs.BlockchainType",
            "name": "blockchainType",
            "type": "uint8"
          },
          {
            "internalType": "uint32",
            "name": "endpointId",
            "type": "uint32"
          }
        ],
        "internalType": "struct TokenKey",
        "name": "key",
        "type": "tuple"
      },
      {
        "internalType": "string",
        "name": "name",
        "type": "string"
      },
      {
        "internalType": "string",
        "name": "symbol",
        "type": "string"
      },
      {
        "internalType": "string",
        "name": "uri",
        "type": "string"
      }
    ],
    "name": "registerToken",
    "outputs": [
      {
        "internalType": "bool",
        "name": "success",
        "type": "bool"
      }
    ],
    "stateMutability": "nonpayable",
    "type": "function"
  },
  {
    "inputs": [
      {
        "internalType": "bytes32",
        "name": "_templateId",
        "type": "bytes32"
      }
    ],
    "name": "resetAdapterTemplate",
    "outputs": [
      {
        "internalType": "bool",
        "name": "success",
        "type": "bool"
      }
    ],
    "stateMutability": "nonpayable",
    "type": "function"
  },
  {
    "inputs": [
      {
        "internalType": "bytes32",
        "name": "_templateId",
        "type": "bytes32"
      }
    ],
    "name": "resetTokenTemplate",
    "outputs": [
      {
        "internalType": "bool",
        "name": "success",
        "type": "bool"
      }
    ],
    "stateMutability": "nonpayable",
    "type": "function"
  },
  {
    "inputs": [
      {
        "internalType": "address",
        "name": "_contract",
        "type": "address"
      }
    ],
    "name": "sendWhitelist",
    "outputs": [
      {
        "internalType": "bool",
        "name": "whitelisted",
        "type": "bool"
      }
    ],
    "stateMutability": "view",
    "type": "function"
  },
  {
    "inputs": [
      {
        "internalType": "enum FactoryLogic.AdapterType",
        "name": "adapterType",
        "type": "uint8"
      },
      {
        "internalType": "address",
        "name": "_implementationAddress",
        "type": "address"
      }
    ],
    "name": "setAdapterTemplate",
    "outputs": [
      {
        "internalType": "bytes32",
        "name": "templateId",
        "type": "bytes32"
      }
    ],
    "stateMutability": "nonpayable",
    "type": "function"
  },
  {
    "inputs": [
      {
        "internalType": "uint32",
        "name": "endpointId",
        "type": "uint32"
      },
      {
        "components": [
          {
            "internalType": "bytes32",
            "name": "originAddress",
            "type": "bytes32"
          },
          {
            "internalType": "uint256",
            "name": "collectibleId",
            "type": "uint256"
          },
          {
            "internalType": "enum TokenDefs.TokenType",
            "name": "tokenType",
            "type": "uint8"
          },
          {
            "internalType": "enum TokenDefs.BlockchainType",
            "name": "blockchainType",
            "type": "uint8"
          },
          {
            "internalType": "uint32",
            "name": "endpointId",
            "type": "uint32"
          }
        ],
        "internalType": "struct TokenKey",
        "name": "key",
        "type": "tuple"
      },
      {
        "internalType": "bytes32",
        "name": "peerAddress",
        "type": "bytes32"
      }
    ],
    "name": "setPeer",
    "outputs": [],
    "stateMutability": "nonpayable",
    "type": "function"
  },
  {
    "inputs": [
      {
        "internalType": "uint16",
        "name": "durationBlocks",
        "type": "uint16"
      },
      {
        "internalType": "uint16",
        "name": "startPercentageBps",
        "type": "uint16"
      }
    ],
    "name": "setProtocolBonusConfig",
    "outputs": [],
    "stateMutability": "nonpayable",
    "type": "function"
  },
  {
    "inputs": [
      {
        "internalType": "uint8",
        "name": "activity",
        "type": "uint8"
      },
      {
        "internalType": "uint16",
        "name": "feeBps",
        "type": "uint16"
      }
    ],
    "name": "setProtocolFee",
    "outputs": [],
    "stateMutability": "nonpayable",
    "type": "function"
  },
  {
    "inputs": [
      {
        "internalType": "uint8[]",
        "name": "activities",
        "type": "uint8[]"
      },
      {
        "internalType": "uint16[]",
        "name": "feesBps",
        "type": "uint16[]"
      }
    ],
    "name": "setProtocolFees",
    "outputs": [],
    "stateMutability": "nonpayable",
    "type": "function"
  },
  {
    "inputs": [
      {
        "internalType": "uint8",
        "name": "activity",
        "type": "uint8"
      },
      {
        "internalType": "uint16",
        "name": "maxFeeBps",
        "type": "uint16"
      }
    ],
    "name": "setProtocolLimit",
    "outputs": [],
    "stateMutability": "nonpayable",
    "type": "function"
  },
  {
    "inputs": [
      {
        "internalType": "uint8[]",
        "name": "activities",
        "type": "uint8[]"
      },
      {
        "internalType": "uint16[]",
        "name": "maxFeesBps",
        "type": "uint16[]"
      }
    ],
    "name": "setProtocolLimits",
    "outputs": [],
    "stateMutability": "nonpayable",
    "type": "function"
  },
  {
    "inputs": [
      {
        "internalType": "address",
        "name": "referee",
        "type": "address"
      },
      {
        "internalType": "address",
        "name": "referrer",
        "type": "address"
      }
    ],
    "name": "setReferral",
    "outputs": [],
    "stateMutability": "nonpayable",
    "type": "function"
  },
  {
    "inputs": [
      {
        "internalType": "address",
        "name": "referee",
        "type": "address"
      },
      {
        "internalType": "bool",
        "name": "rewardActive",
        "type": "bool"
      },
      {
        "internalType": "bool",
        "name": "discountActive",
        "type": "bool"
      }
    ],
    "name": "setReferralStatus",
    "outputs": [],
    "stateMutability": "nonpayable",
    "type": "function"
  },
  {
    "inputs": [
      {
        "internalType": "address",
        "name": "newController",
        "type": "address"
      }
    ],
    "name": "setReferralsController",
    "outputs": [],
    "stateMutability": "nonpayable",
    "type": "function"
  },
  {
    "inputs": [
      {
        "internalType": "enum TokenDefs.TokenType",
        "name": "tokenType",
        "type": "uint8"
      },
      {
        "internalType": "address",
        "name": "_implementationAddress",
        "type": "address"
      },
      {
        "internalType": "uint256",
        "name": "totalSupply",
        "type": "uint256"
      }
    ],
    "name": "setTokenTemplate",
    "outputs": [
      {
        "internalType": "bytes32",
        "name": "templateId",
        "type": "bytes32"
      }
    ],
    "stateMutability": "nonpayable",
    "type": "function"
  },
  {
    "inputs": [
      {
        "internalType": "uint32",
        "name": "endpointId",
        "type": "uint32"
      },
      {
        "components": [
          {
            "internalType": "bytes32",
            "name": "originAddress",
            "type": "bytes32"
          },
          {
            "internalType": "uint256",
            "name": "collectibleId",
            "type": "uint256"
          },
          {
            "internalType": "enum TokenDefs.TokenType",
            "name": "tokenType",
            "type": "uint8"
          },
          {
            "internalType": "enum TokenDefs.BlockchainType",
            "name": "blockchainType",
            "type": "uint8"
          },
          {
            "internalType": "uint32",
            "name": "endpointId",
            "type": "uint32"
          }
        ],
        "internalType": "struct TokenKey",
        "name": "key",
        "type": "tuple"
      }
    ],
    "name": "setupOApp",
    "outputs": [],
    "stateMutability": "nonpayable",
    "type": "function"
  },
  {
    "inputs": [
      {
        "internalType": "TokenId",
        "name": "id",
        "type": "bytes32"
      }
    ],
    "name": "solanaSalt",
    "outputs": [
      {
        "internalType": "bytes32",
        "name": "solanaSalt",
        "type": "bytes32"
      }
    ],
    "stateMutability": "view",
    "type": "function"
  },
  {
    "inputs": [],
    "name": "swapRouter",
    "outputs": [
      {
        "internalType": "address",
        "name": "",
        "type": "address"
      }
    ],
    "stateMutability": "view",
    "type": "function"
  },
  {
    "inputs": [
      {
        "internalType": "address",
        "name": "managerAddress",
        "type": "address"
      },
      {
        "internalType": "bool",
        "name": "authorized",
        "type": "bool"
      }
    ],
    "name": "toggleManager",
    "outputs": [],
    "stateMutability": "nonpayable",
    "type": "function"
  },
  {
    "inputs": [
      {
        "internalType": "address",
        "name": "_contract",
        "type": "address"
      },
      {
        "internalType": "bool",
        "name": "_whitelist",
        "type": "bool"
      }
    ],
    "name": "toggleWhitelist",
    "outputs": [],
    "stateMutability": "nonpayable",
    "type": "function"
  },
  {
    "inputs": [
      {
        "internalType": "bytes32",
        "name": "tokenAddressAndId",
        "type": "bytes32"
      }
    ],
    "name": "tokenAddressAndIdToTokenId",
    "outputs": [
      {
        "internalType": "TokenId",
        "name": "id",
        "type": "bytes32"
      }
    ],
    "stateMutability": "view",
    "type": "function"
  },
  {
    "inputs": [
      {
        "internalType": "TokenId",
        "name": "id",
        "type": "bytes32"
      }
    ],
    "name": "tokenIdToTokenKey",
    "outputs": [
      {
        "internalType": "bytes32",
        "name": "originAddress",
        "type": "bytes32"
      },
      {
        "internalType": "uint256",
        "name": "collectibleId",
        "type": "uint256"
      },
      {
        "internalType": "enum TokenDefs.TokenType",
        "name": "tokenType",
        "type": "uint8"
      },
      {
        "internalType": "enum TokenDefs.BlockchainType",
        "name": "blockchainType",
        "type": "uint8"
      },
      {
        "internalType": "uint32",
        "name": "endpointId",
        "type": "uint32"
      }
    ],
    "stateMutability": "view",
    "type": "function"
  },
  {
    "inputs": [
      {
        "internalType": "bytes32",
        "name": "templateId",
        "type": "bytes32"
      }
    ],
    "name": "tokenTemplates",
    "outputs": [
      {
        "internalType": "enum TokenDefs.TokenType",
        "name": "tokenType",
        "type": "uint8"
      },
      {
        "internalType": "address",
        "name": "implementationAddress",
        "type": "address"
      },
      {
        "internalType": "uint256",
        "name": "totalSupply",
        "type": "uint256"
      }
    ],
    "stateMutability": "view",
    "type": "function"
  },
  {
    "inputs": [
      {
        "internalType": "TokenId",
        "name": "id",
        "type": "bytes32"
      }
    ],
    "name": "tokenToEndpointTokenId",
    "outputs": [
      {
        "internalType": "uint256",
        "name": "endpointTokenId",
        "type": "uint256"
      }
    ],
    "stateMutability": "view",
    "type": "function"
  },
  {
    "inputs": [
      {
        "internalType": "TokenId",
        "name": "id",
        "type": "bytes32"
      }
    ],
    "name": "tokenToTemplateId",
    "outputs": [
      {
        "internalType": "bytes32",
        "name": "templateId",
        "type": "bytes32"
      }
    ],
    "stateMutability": "view",
    "type": "function"
  },
  {
    "inputs": [
      {
        "internalType": "address",
        "name": "newOwner",
        "type": "address"
      }
    ],
    "name": "transferOwnership",
    "outputs": [],
    "stateMutability": "nonpayable",
    "type": "function"
  },
  {
    "inputs": [],
    "name": "trustedForwarder",
    "outputs": [
      {
        "internalType": "address",
        "name": "",
        "type": "address"
      }
    ],
    "stateMutability": "view",
    "type": "function"
  },
  {
    "inputs": [
      {
        "internalType": "uint32",
        "name": "endpointId",
        "type": "uint32"
      },
      {
        "components": [
          {
            "internalType": "bytes32",
            "name": "originAddress",
            "type": "bytes32"
          },
          {
            "internalType": "uint256",
            "name": "collectibleId",
            "type": "uint256"
          },
          {
            "internalType": "enum TokenDefs.TokenType",
            "name": "tokenType",
            "type": "uint8"
          },
          {
            "internalType": "enum TokenDefs.BlockchainType",
            "name": "blockchainType",
            "type": "uint8"
          },
          {
            "internalType": "uint32",
            "name": "endpointId",
            "type": "uint32"
          }
        ],
        "internalType": "struct TokenKey",
        "name": "key",
        "type": "tuple"
      }
    ],
    "name": "updateOAppConfigs",
    "outputs": [],
    "stateMutability": "nonpayable",
    "type": "function"
  },
  {
    "inputs": [
      {
        "internalType": "address",
        "name": "user",
        "type": "address"
      },
      {
        "internalType": "address",
        "name": "builder",
        "type": "address"
      },
      {
        "internalType": "uint8",
        "name": "activity",
        "type": "uint8"
      },
      {
        "internalType": "uint64",
        "name": "feeBps",
        "type": "uint64"
      }
    ],
    "name": "validateBuilderFee",
    "outputs": [],
    "stateMutability": "view",
    "type": "function"
  },
  {
    "anonymous": false,
    "inputs": [
      {
        "indexed": true,
        "internalType": "address",
        "name": "adapter",
        "type": "address"
      },
      {
        "indexed": true,
        "internalType": "address",
        "name": "externalToken",
        "type": "address"
      },
      {
        "indexed": true,
        "internalType": "address",
        "name": "wrappedToken",
        "type": "address"
      },
      {
        "indexed": false,
        "internalType": "uint8",
        "name": "adapterType",
        "type": "uint8"
      }
    ],
    "name": "AdapterDeployed",
    "type": "event"
  },
  {
    "anonymous": false,
    "inputs": [
      {
        "indexed": true,
        "internalType": "bytes32",
        "name": "templateId",
        "type": "bytes32"
      }
    ],
    "name": "AdapterTemplateReset",
    "type": "event"
  },
  {
    "anonymous": false,
    "inputs": [
      {
        "indexed": true,
        "internalType": "bytes32",
        "name": "templateId",
        "type": "bytes32"
      },
      {
        "indexed": false,
        "internalType": "uint8",
        "name": "adapterType",
        "type": "uint8"
      },
      {
        "indexed": false,
        "internalType": "address",
        "name": "implementationAddress",
        "type": "address"
      }
    ],
    "name": "AdapterTemplateSet",
    "type": "event"
  },
  {
    "anonymous": false,
    "inputs": [
      {
        "indexed": true,
        "internalType": "address",
        "name": "user",
        "type": "address"
      },
      {
        "indexed": true,
        "internalType": "address",
        "name": "builder",
        "type": "address"
      },
      {
        "components": [
          {
            "internalType": "uint8",
            "name": "activity",
            "type": "uint8"
          },
          {
            "internalType": "uint16",
            "name": "maxFeeBps",
            "type": "uint16"
          }
        ],
        "indexed": false,
        "internalType": "struct FeesConfigV2.ApprovalEntry[]",
        "name": "approvals",
        "type": "tuple[]"
      }
    ],
    "name": "BuilderFeesApproved",
    "type": "event"
  },
  {
    "anonymous": false,
    "inputs": [
      {
        "indexed": true,
        "internalType": "address",
        "name": "coinAddress",
        "type": "address"
      },
      {
        "indexed": true,
        "internalType": "uint256",
        "name": "hubId",
        "type": "uint256"
      },
      {
        "indexed": false,
        "internalType": "string",
        "name": "name",
        "type": "string"
      },
      {
        "indexed": false,
        "internalType": "string",
        "name": "symbol",
        "type": "string"
      },
      {
        "indexed": false,
        "internalType": "uint8",
        "name": "decimals",
        "type": "uint8"
      },
      {
        "indexed": false,
        "internalType": "string",
        "name": "tokenURI",
        "type": "string"
      },
      {
        "indexed": false,
        "internalType": "uint256",
        "name": "totalSupply",
        "type": "uint256"
      }
    ],
    "name": "CoinCreated",
    "type": "event"
  },
  {
    "anonymous": false,
    "inputs": [
      {
        "indexed": true,
        "internalType": "bytes32",
        "name": "identifier",
        "type": "bytes32"
      },
      {
        "indexed": true,
        "internalType": "address",
        "name": "oldAddress",
        "type": "address"
      },
      {
        "indexed": true,
        "internalType": "address",
        "name": "newAddress",
        "type": "address"
      }
    ],
    "name": "ContractAddressOverwritten",
    "type": "event"
  },
  {
    "anonymous": false,
    "inputs": [
      {
        "indexed": true,
        "internalType": "bytes32",
        "name": "name",
        "type": "bytes32"
      },
      {
        "indexed": true,
        "internalType": "address",
        "name": "contractAddress",
        "type": "address"
      },
      {
        "indexed": false,
        "internalType": "bytes32",
        "name": "salt",
        "type": "bytes32"
      }
    ],
    "name": "ContractDeployed",
    "type": "event"
  },
  {
    "anonymous": false,
    "inputs": [
      {
        "indexed": true,
        "internalType": "TokenId",
        "name": "tokenId",
        "type": "bytes32"
      },
      {
        "indexed": true,
        "internalType": "address",
        "name": "tokenAddress",
        "type": "address"
      },
      {
        "indexed": true,
        "internalType": "address",
        "name": "adapter",
        "type": "address"
      },
      {
        "indexed": false,
        "internalType": "address",
        "name": "externalToken",
        "type": "address"
      },
      {
        "indexed": false,
        "internalType": "string",
        "name": "name",
        "type": "string"
      },
      {
        "indexed": false,
        "internalType": "string",
        "name": "symbol",
        "type": "string"
      },
      {
        "indexed": false,
        "internalType": "uint8",
        "name": "adapterType",
        "type": "uint8"
      }
    ],
    "name": "ExternalTokenCreated",
    "type": "event"
  },
  {
    "anonymous": false,
    "inputs": [
      {
        "indexed": true,
        "internalType": "uint256",
        "name": "id",
        "type": "uint256"
      },
      {
        "indexed": true,
        "internalType": "address",
        "name": "creator",
        "type": "address"
      },
      {
        "indexed": false,
        "internalType": "address",
        "name": "receiver",
        "type": "address"
      },
      {
        "indexed": false,
        "internalType": "bool",
        "name": "isPrivate",
        "type": "bool"
      }
    ],
    "name": "HubCreated",
    "type": "event"
  },
  {
    "anonymous": false,
    "inputs": [
      {
        "indexed": false,
        "internalType": "address",
        "name": "newAddress",
        "type": "address"
      }
    ],
    "name": "HubsAddressChanged",
    "type": "event"
  },
  {
    "anonymous": false,
    "inputs": [
      {
        "indexed": false,
        "internalType": "uint64",
        "name": "version",
        "type": "uint64"
      }
    ],
    "name": "Initialized",
    "type": "event"
  },
  {
    "anonymous": false,
    "inputs": [
      {
        "indexed": true,
        "internalType": "uint256",
        "name": "id",
        "type": "uint256"
      },
      {
        "indexed": true,
        "internalType": "uint256",
        "name": "hubId",
        "type": "uint256"
      },
      {
        "indexed": true,
        "internalType": "string",
        "name": "symbol",
        "type": "string"
      },
      {
        "indexed": false,
        "internalType": "string",
        "name": "name",
        "type": "string"
      },
      {
        "indexed": false,
        "internalType": "string",
        "name": "tokenUri",
        "type": "string"
      },
      {
        "indexed": false,
        "internalType": "uint8",
        "name": "decimals",
        "type": "uint8"
      },
      {
        "indexed": false,
        "internalType": "uint256",
        "name": "poolType",
        "type": "uint256"
      }
    ],
    "name": "ItemCreated",
    "type": "event"
  },
  {
    "anonymous": false,
    "inputs": [
      {
        "indexed": false,
        "internalType": "address",
        "name": "newAddress",
        "type": "address"
      }
    ],
    "name": "ItemsAddressChanged",
    "type": "event"
  },
  {
    "anonymous": false,
    "inputs": [
      {
        "indexed": false,
        "internalType": "address",
        "name": "newAddress",
        "type": "address"
      }
    ],
    "name": "LaunchpadAddressChanged",
    "type": "event"
  },
  {
    "anonymous": false,
    "inputs": [
      {
        "indexed": false,
        "internalType": "address",
        "name": "newAddress",
        "type": "address"
      }
    ],
    "name": "LiquidityManagerAddressChanged",
    "type": "event"
  },
  {
    "anonymous": false,
    "inputs": [
      {
        "indexed": false,
        "internalType": "address",
        "name": "newAddress",
        "type": "address"
      }
    ],
    "name": "LiquidityMigratorAddressChanged",
    "type": "event"
  },
  {
    "anonymous": false,
    "inputs": [
      {
        "indexed": true,
        "internalType": "address",
        "name": "manager",
        "type": "address"
      },
      {
        "indexed": false,
        "internalType": "bool",
        "name": "authorized",
        "type": "bool"
      }
    ],
    "name": "ManagerUpdated",
    "type": "event"
  },
  {
    "anonymous": false,
    "inputs": [
      {
        "indexed": true,
        "internalType": "uint32",
        "name": "endpointId",
        "type": "uint32"
      },
      {
        "indexed": true,
        "internalType": "TokenId",
        "name": "tokenId",
        "type": "bytes32"
      },
      {
        "indexed": false,
        "internalType": "address",
        "name": "tokenAddress",
        "type": "address"
      },
      {
        "indexed": false,
        "internalType": "address",
        "name": "sendLibrary",
        "type": "address"
      },
      {
        "indexed": false,
        "internalType": "address",
        "name": "receiveLibrary",
        "type": "address"
      }
    ],
    "name": "OAppConfigured",
    "type": "event"
  },
  {
    "anonymous": false,
    "inputs": [
      {
        "indexed": true,
        "internalType": "address",
        "name": "user",
        "type": "address"
      },
      {
        "indexed": true,
        "internalType": "address",
        "name": "newOwner",
        "type": "address"
      }
    ],
    "name": "OwnershipTransferred",
    "type": "event"
  },
  {
    "anonymous": false,
    "inputs": [
      {
        "indexed": true,
        "internalType": "uint32",
        "name": "endpointId",
        "type": "uint32"
      },
      {
        "indexed": true,
        "internalType": "TokenId",
        "name": "tokenId",
        "type": "bytes32"
      },
      {
        "indexed": false,
        "internalType": "address",
        "name": "tokenAddress",
        "type": "address"
      },
      {
        "indexed": false,
        "internalType": "bytes32",
        "name": "peerAddress",
        "type": "bytes32"
      }
    ],
    "name": "PeerSet",
    "type": "event"
  },
  {
    "anonymous": false,
    "inputs": [
      {
        "indexed": true,
        "internalType": "uint256",
        "name": "id",
        "type": "uint256"
      },
      {
        "indexed": true,
        "internalType": "uint256",
        "name": "hubId",
        "type": "uint256"
      },
      {
        "indexed": false,
        "internalType": "string",
        "name": "name",
        "type": "string"
      },
      {
        "indexed": false,
        "internalType": "string",
        "name": "symbol",
        "type": "string"
      },
      {
        "indexed": false,
        "internalType": "string",
        "name": "uri",
        "type": "string"
      },
      {
        "indexed": false,
        "internalType": "bool",
        "name": "soulbound",
        "type": "bool"
      }
    ],
    "name": "PointsCreated",
    "type": "event"
  },
  {
    "anonymous": false,
    "inputs": [
      {
        "indexed": false,
        "internalType": "uint16",
        "name": "durationBlocks",
        "type": "uint16"
      },
      {
        "indexed": false,
        "internalType": "uint16",
        "name": "startPercentageBps",
        "type": "uint16"
      }
    ],
    "name": "ProtocolBonusConfigSet",
    "type": "event"
  },
  {
    "anonymous": false,
    "inputs": [
      {
        "indexed": true,
        "internalType": "uint8",
        "name": "activity",
        "type": "uint8"
      },
      {
        "indexed": false,
        "internalType": "uint16",
        "name": "feeBps",
        "type": "uint16"
      }
    ],
    "name": "ProtocolFeeSet",
    "type": "event"
  },
  {
    "anonymous": false,
    "inputs": [
      {
        "indexed": true,
        "internalType": "uint8",
        "name": "activity",
        "type": "uint8"
      },
      {
        "indexed": false,
        "internalType": "uint16",
        "name": "maxFeeBps",
        "type": "uint16"
      }
    ],
    "name": "ProtocolLimitSet",
    "type": "event"
  },
  {
    "anonymous": false,
    "inputs": [
      {
        "indexed": true,
        "internalType": "address",
        "name": "referee",
        "type": "address"
      },
      {
        "indexed": true,
        "internalType": "address",
        "name": "referrer",
        "type": "address"
      },
      {
        "indexed": false,
        "internalType": "bool",
        "name": "rewardActive",
        "type": "bool"
      },
      {
        "indexed": false,
        "internalType": "bool",
        "name": "discountActive",
        "type": "bool"
      }
    ],
    "name": "ReferralSet",
    "type": "event"
  },
  {
    "anonymous": false,
    "inputs": [
      {
        "indexed": true,
        "internalType": "address",
        "name": "referee",
        "type": "address"
      },
      {
        "indexed": false,
        "internalType": "bool",
        "name": "rewardActive",
        "type": "bool"
      },
      {
        "indexed": false,
        "internalType": "bool",
        "name": "discountActive",
        "type": "bool"
      }
    ],
    "name": "ReferralStatusUpdated",
    "type": "event"
  },
  {
    "anonymous": false,
    "inputs": [
      {
        "indexed": true,
        "internalType": "address",
        "name": "oldController",
        "type": "address"
      },
      {
        "indexed": true,
        "internalType": "address",
        "name": "newController",
        "type": "address"
      }
    ],
    "name": "ReferralsControllerUpdated",
    "type": "event"
  },
  {
    "anonymous": false,
    "inputs": [
      {
        "indexed": true,
        "internalType": "address",
        "name": "owner",
        "type": "address"
      },
      {
        "indexed": false,
        "internalType": "address",
        "name": "trustedForwarder",
        "type": "address"
      },
      {
        "indexed": false,
        "internalType": "address",
        "name": "paymentToken",
        "type": "address"
      },
      {
        "indexed": false,
        "internalType": "address",
        "name": "protocolFeeTo",
        "type": "address"
      },
      {
        "indexed": false,
        "internalType": "address",
        "name": "endpoint",
        "type": "address"
      },
      {
        "indexed": false,
        "internalType": "address",
        "name": "swapRouter",
        "type": "address"
      }
    ],
    "name": "RegistryInitialized",
    "type": "event"
  },
  {
    "anonymous": false,
    "inputs": [
      {
        "indexed": true,
        "internalType": "address",
        "name": "tokenAddress",
        "type": "address"
      },
      {
        "indexed": true,
        "internalType": "uint256",
        "name": "tokenId",
        "type": "uint256"
      },
      {
        "indexed": true,
        "internalType": "uint256",
        "name": "hubId",
        "type": "uint256"
      },
      {
        "indexed": false,
        "internalType": "string",
        "name": "symbol",
        "type": "string"
      },
      {
        "indexed": false,
        "internalType": "string",
        "name": "name",
        "type": "string"
      },
      {
        "indexed": false,
        "internalType": "string",
        "name": "tokenUri",
        "type": "string"
      },
      {
        "indexed": false,
        "internalType": "uint8",
        "name": "decimals",
        "type": "uint8"
      }
    ],
    "name": "TokenCreated",
    "type": "event"
  },
  {
    "anonymous": false,
    "inputs": [
      {
        "indexed": true,
        "internalType": "TokenId",
        "name": "tokenId",
        "type": "bytes32"
      },
      {
        "indexed": true,
        "internalType": "address",
        "name": "tokenAddress",
        "type": "address"
      },
      {
        "indexed": true,
        "internalType": "bytes32",
        "name": "templateId",
        "type": "bytes32"
      },
      {
        "indexed": false,
        "internalType": "string",
        "name": "name",
        "type": "string"
      },
      {
        "indexed": false,
        "internalType": "string",
        "name": "symbol",
        "type": "string"
      }
    ],
    "name": "TokenRegistered",
    "type": "event"
  },
  {
    "anonymous": false,
    "inputs": [
      {
        "indexed": true,
        "internalType": "bytes32",
        "name": "templateId",
        "type": "bytes32"
      }
    ],
    "name": "TokenTemplateReset",
    "type": "event"
  },
  {
    "anonymous": false,
    "inputs": [
      {
        "indexed": true,
        "internalType": "bytes32",
        "name": "templateId",
        "type": "bytes32"
      },
      {
        "indexed": false,
        "internalType": "uint8",
        "name": "tokenType",
        "type": "uint8"
      },
      {
        "indexed": false,
        "internalType": "address",
        "name": "implementationAddress",
        "type": "address"
      },
      {
        "indexed": false,
        "internalType": "uint256",
        "name": "totalSupply",
        "type": "uint256"
      }
    ],
    "name": "TokenTemplateSet",
    "type": "event"
  },
  {
    "anonymous": false,
    "inputs": [
      {
        "indexed": true,
        "internalType": "address",
        "name": "contractAddress",
        "type": "address"
      },
      {
        "indexed": false,
        "internalType": "bool",
        "name": "whitelisted",
        "type": "bool"
      }
    ],
    "name": "WhitelistToggled",
    "type": "event"
  },
  {
    "inputs": [
      {
        "internalType": "address",
        "name": "user",
        "type": "address"
      },
      {
        "internalType": "address",
        "name": "builder",
        "type": "address"
      },
      {
        "internalType": "uint8",
        "name": "activity",
        "type": "uint8"
      },
      {
        "internalType": "uint64",
        "name": "requestedFee",
        "type": "uint64"
      },
      {
        "internalType": "uint16",
        "name": "approvedFee",
        "type": "uint16"
      }
    ],
    "name": "BuilderFeeNotApproved",
    "type": "error"
  },
  {
    "inputs": [
      {
        "internalType": "uint8",
        "name": "activity",
        "type": "uint8"
      }
    ],
    "name": "DuplicateActivity",
    "type": "error"
  },
  {
    "inputs": [
      {
        "internalType": "uint8",
        "name": "activity",
        "type": "uint8"
      },
      {
        "internalType": "uint64",
        "name": "requestedFee",
        "type": "uint64"
      },
      {
        "internalType": "uint16",
        "name": "protocolLimit",
        "type": "uint16"
      }
    ],
    "name": "ExceedsProtocolLimit",
    "type": "error"
  },
  {
    "inputs": [
      {
        "internalType": "uint16",
        "name": "fee",
        "type": "uint16"
      }
    ],
    "name": "InvalidFee",
    "type": "error"
  },
  {
    "inputs": [],
    "name": "InvalidInitialization",
    "type": "error"
  },
  {
    "inputs": [],
    "name": "MissingMetadata",
    "type": "error"
  },
  {
    "inputs": [],
    "name": "MissingReceiver",
    "type": "error"
  },
  {
    "inputs": [
      {
        "internalType": "uint8",
        "name": "activity",
        "type": "uint8"
      }
    ],
    "name": "NoProtocolLimitSet",
    "type": "error"
  },
  {
    "inputs": [],
    "name": "NotInitializing",
    "type": "error"
  },
  {
    "inputs": [],
    "name": "ReentrancyGuardReentrantCall",
    "type": "error"
  },
  {
    "inputs": [
      {
        "internalType": "uint256",
        "name": "count",
        "type": "uint256"
      }
    ],
    "name": "TooManyEntries",
    "type": "error"
  },
  {
    "inputs": [],
    "name": "Unauthorized",
    "type": "error"
  },
  {
    "inputs": [],
    "name": "UnauthorizedReferralsController",
    "type": "error"
  }
]